tdfextractor/__init__.py
tdfextractor/cli_args.py
tdfextractor/constants.py
tdfextractor/mgf_exctractor.py
tdfextractor/ms2_extractor.py
tdfextractor/utils.py
tdfextractor-0.3.0.dist-info/licenses/LICENSE
tdfextractor-0.3.0.dist-info/METADATA
tdfextractor-0.3.0.dist-info/WHEEL
tdfextractor-0.3.0.dist-info/entry_points.txt
tdfextractor-0.3.0.dist-info/top_level.txt
tdfextractor-0.3.0.dist-info/RECORD
