Metadata-Version: 2.4
Name: tdfextractor
Version: 0.3.0
Summary: extract ms2/mgf files from bruker d folders
Author-email: Patrick Garrett <pgarrett@scripps.edu>
License: MIT License
Classifier: Programming Language :: Python :: 3
Classifier: Development Status :: 4 - Beta
Classifier: License :: OSI Approved :: MIT License
Classifier: Operating System :: OS Independent
Requires-Python: >=3.8
License-File: LICENSE
Requires-Dist: tdfpy==0.1.7
Requires-Dist: serenipy==0.3.0
Requires-Dist: tqdm
Dynamic: license-file
